gitpub/__init__.py
gitpub/gitpub.py
gitpub-1.0.dist-info/DESCRIPTION.rst
gitpub-1.0.dist-info/METADATA
gitpub-1.0.dist-info/RECORD
gitpub-1.0.dist-info/WHEEL
gitpub-1.0.dist-info/entry_points.txt
gitpub-1.0.dist-info/metadata.json
gitpub-1.0.dist-info/top_level.txt
samples/__init__.py
samples/most_popular_repo.py
tests/__init__.py
tests/test_gitpub.py
