Metadata-Version: 2.0
Name: gitpub
Version: 1.0
Summary: a module to interact with Github's API
Home-page: https://github.com/demfier/gitpub
Author: Gaurav Sahu
Author-email: sahu.gaurav719@googlemail.com
License: MIT
Keywords: github api development interact
Platform: UNKNOWN
Classifier: Development Status :: 2 - Pre-Alpha
Classifier: Intended Audience :: Developers
Classifier: License :: OSI Approved :: MIT License
Requires-Dist: peppercorn
